vectorstores/__init__.py
vectorstores/base.py
vectorstores/vectorstores.py
vectorstores-0.1.2.dev50.dist-info/licenses/LICENSE
vectorstores-0.1.2.dev50.dist-info/METADATA
vectorstores-0.1.2.dev50.dist-info/WHEEL
vectorstores-0.1.2.dev50.dist-info/top_level.txt
vectorstores-0.1.2.dev50.dist-info/RECORD
